{
  "type": "Feature",
  "properties": {
    "gn:admin1_code":"01",
    "gn:asciiname":"Newton Terrace",
    "gn:country_code":"BB",
    "gn:dem":69,
    "gn:feature_class":"P",
    "gn:feature_code":"PPL",
    "gn:name":"Newton Terrace",
    "gn:population":0,
    "gn:timezone":"America/Barbados",
    "iso:country":"BB",
    "wof:name":"Newton Terrace",
    "wof:placetype":"locality"
},
  "geometry": {"coordinates":[-59.53144,13.07758],"type":"Point"}
}