{
  "type": "Feature",
  "properties": {
    "gn:country":"BB",
    "gn:fcode":"PPL",
    "gn:pop":1765,
    "iso:country":"BB",
    "name:ceb_x_preferred":[
        "Bathsheba"
    ],
    "name:deu_x_preferred":[
        "Bathsheba"
    ],
    "name:ell_x_preferred":[
        "\u039c\u03c0\u03b1\u03b8\u03c3\u03ae\u03bc\u03c0\u03b1"
    ],
    "name:eng_x_preferred":[
        "Bathsheba"
    ],
    "name:fas_x_preferred":[
        "\u0628\u062b\u200c\u0634\u0628\u0639"
    ],
    "name:fra_x_preferred":[
        "Bathsheba"
    ],
    "name:heb_x_preferred":[
        "\u05d1\u05ea \u05e9\u05d1\u05e2"
    ],
    "name:lit_x_preferred":[
        "Bat\u0161eba"
    ],
    "name:nld_x_preferred":[
        "Bathsheba"
    ],
    "name:pol_x_preferred":[
        "Bathsheba"
    ],
    "name:por_x_preferred":[
        "Bathsheba"
    ],
    "name:ron_x_preferred":[
        "Bathsheba"
    ],
    "name:spa_x_preferred":[
        "Bathsheba"
    ],
    "name:swe_x_preferred":[
        "Bathsheba"
    ],
    "name:urd_x_preferred":[
        "\u0628\u062b\u0634\u0628\u0639\u060c \u0628\u0627\u0631\u0628\u0627\u0688\u0648\u0633"
    ],
    "name:urd_x_variant":[
        "\u0628\u062b\u0634\u0628\u0639"
    ],
    "qs:name":"Bathsheba",
    "qs:photos_9r":0,
    "qs:photos_sr":0,
    "qs:pop_sr":"3",
    "wd:wordcount":2378,
    "wof:name":"Bathsheba",
    "wof:placetype":"locality",
    "wof:population":1765
},
  "geometry": {"coordinates":[-59.51667,13.21667],"type":"Point"}
}