{
  "type": "Feature",
  "properties": {
    "gn:admin1_code":"08",
    "gn:asciiname":"Two Mile Hill",
    "gn:country_code":"BB",
    "gn:dem":65,
    "gn:feature_class":"P",
    "gn:feature_code":"PPL",
    "gn:name":"Two Mile Hill",
    "gn:population":0,
    "gn:timezone":"America/Barbados",
    "iso:country":"BB",
    "wof:name":"Two Mile Hill",
    "wof:placetype":"locality"
},
  "geometry": {"coordinates":[-59.58534,13.1045],"type":"Point"}
}