{
  "type": "Feature",
  "properties": {
    "gn:admin1_code":"10",
    "gn:asciiname":"Industry Hall",
    "gn:country_code":"BB",
    "gn:dem":31,
    "gn:feature_class":"P",
    "gn:feature_code":"PPL",
    "gn:name":"Industry Hall",
    "gn:population":0,
    "gn:timezone":"America/Barbados",
    "iso:country":"BB",
    "wof:name":"Industry Hall",
    "wof:placetype":"locality"
},
  "geometry": {"coordinates":[-59.43303,13.15784],"type":"Point"}
}