{
  "type": "Feature",
  "properties": {
    "gn:admin1_code":"11",
    "gn:asciiname":"Lears",
    "gn:country_code":"BB",
    "gn:dem":86,
    "gn:feature_class":"P",
    "gn:feature_code":"PPL",
    "gn:name":"Lears",
    "gn:population":0,
    "gn:timezone":"America/Barbados",
    "iso:country":"BB",
    "wof:name":"Lears",
    "wof:placetype":"locality"
},
  "geometry": {"coordinates":[-59.59366,13.14288],"type":"Point"}
}