{
  "type": "Feature",
  "properties": {
    "iso:country":"BB",
    "name:ceb_x_preferred":[
        "Windy Ridge"
    ],
    "name:swe_x_preferred":[
        "Windy Ridge"
    ],
    "qs:gn_pop":0,
    "qs:name":"Windy Ridge",
    "qs:name_adm0":"Barbados",
    "qs:name_adm1":"Saint John",
    "qs:photos":101,
    "qs:photos_1k":20,
    "qs:photos_9k":1,
    "qs:photos_9r":3,
    "qs:photos_all":101,
    "qs:photos_sr":3,
    "qs:placetype":"Town",
    "qs:pop_sr":"0",
    "qs:woe_adm0":23424754,
    "wd:wordcount":105,
    "wof:name":"Windy Ridge",
    "wof:placetype":"locality"
},
  "geometry": {"coordinates":[-59.466333,13.159223],"type":"Point"}
}