{
  "type": "Feature",
  "properties": {
    "gn:admin1_code":"01",
    "gn:asciiname":"Green Garden",
    "gn:country_code":"BB",
    "gn:dem":20,
    "gn:feature_class":"P",
    "gn:feature_code":"PPL",
    "gn:name":"Green Garden",
    "gn:population":0,
    "gn:timezone":"America/Barbados",
    "iso:country":"BB",
    "wof:name":"Green Garden",
    "wof:placetype":"locality"
},
  "geometry": {"coordinates":[-59.525,13.04792],"type":"Point"}
}