{
  "type": "Feature",
  "properties": {
    "gn:admin1_code":"07",
    "gn:asciiname":"Cave Hill",
    "gn:country_code":"BB",
    "gn:dem":68,
    "gn:feature_class":"P",
    "gn:feature_code":"PPL",
    "gn:name":"Cave Hill",
    "gn:population":0,
    "gn:timezone":"America/Barbados",
    "iso:country":"BB",
    "wof:name":"Cave Hill",
    "wof:placetype":"locality"
},
  "geometry": {"coordinates":[-59.58443000000001,13.29968],"type":"Point"}
}