{
  "type": "Feature",
  "properties": {
    "iso:country":"BB",
    "qs:gn_pop":0,
    "qs:name":"Coles Pasture",
    "qs:name_adm0":"Barbados",
    "qs:name_adm1":"Saint Philip",
    "qs:photos":795,
    "qs:photos_1k":161,
    "qs:photos_9k":4,
    "qs:photos_9r":6,
    "qs:photos_all":795,
    "qs:photos_sr":9,
    "qs:placetype":"Town",
    "qs:pop_sr":"0",
    "qs:woe_adm0":23424754,
    "wof:name":"Coles Pasture",
    "wof:placetype":"locality"
},
  "geometry": {"coordinates":[-59.444274,13.108319],"type":"Point"}
}