{
  "type": "Feature",
  "properties": {
    "gn:admin1_code":"03",
    "gn:asciiname":"Constant",
    "gn:country_code":"BB",
    "gn:dem":60,
    "gn:feature_class":"P",
    "gn:feature_code":"PPL",
    "gn:name":"Constant",
    "gn:population":0,
    "gn:timezone":"America/Barbados",
    "iso:country":"BB",
    "wof:name":"Constant",
    "wof:placetype":"locality"
},
  "geometry": {"coordinates":[-59.55856,13.12165],"type":"Point"}
}