{
  "type": "Feature",
  "properties": {
    "gn:admin1_code":"08",
    "gn:asciiname":"Grazettes",
    "gn:country_code":"BB",
    "gn:dem":51,
    "gn:feature_class":"P",
    "gn:feature_code":"PPL",
    "gn:name":"Grazettes",
    "gn:population":0,
    "gn:timezone":"America/Barbados",
    "iso:country":"BB",
    "wof:name":"Grazettes",
    "wof:placetype":"locality"
},
  "geometry": {"coordinates":[-59.61239000000001,13.12827],"type":"Point"}
}