{
  "type": "Feature",
  "properties": {
    "gn:admin1_code":"03",
    "gn:asciiname":"Drax Hall Hope",
    "gn:country_code":"BB",
    "gn:dem":189,
    "gn:feature_class":"P",
    "gn:feature_code":"PPL",
    "gn:name":"Drax Hall Hope",
    "gn:population":0,
    "gn:timezone":"America/Barbados",
    "iso:country":"BB",
    "wof:name":"Drax Hall Hope",
    "wof:placetype":"locality"
},
  "geometry": {"coordinates":[-59.5361,13.14565],"type":"Point"}
}