{
  "type": "Feature",
  "properties": {
    "gn:admin1_code":"06",
    "gn:asciiname":"Branchbury",
    "gn:country_code":"BB",
    "gn:dem":289,
    "gn:feature_class":"P",
    "gn:feature_code":"PPL",
    "gn:name":"Branchbury",
    "gn:population":0,
    "gn:timezone":"America/Barbados",
    "iso:country":"BB",
    "wof:name":"Branchbury",
    "wof:placetype":"locality"
},
  "geometry": {"coordinates":[-59.54933000000001,13.18784],"type":"Point"}
}