{
  "type": "Feature",
  "properties": {
    "gn:admin1_code":"06",
    "gn:asciiname":"Frizers",
    "gn:cc2":"BB",
    "gn:country_code":"BB",
    "gn:dem":138,
    "gn:feature_class":"P",
    "gn:feature_code":"PPL",
    "gn:name":"Frizers",
    "gn:population":0,
    "gn:timezone":"America/Barbados",
    "iso:country":"BB",
    "name:und_x_variant":[
        "Frazers",
        "Frizers"
    ],
    "wof:name":"Frizers",
    "wof:placetype":"locality"
},
  "geometry": {"coordinates":[-59.54337,13.20868],"type":"Point"}
}