{
  "type": "Feature",
  "properties": {
    "gn:admin1_code":"01",
    "gn:asciiname":"Round Rock",
    "gn:country_code":"BB",
    "gn:dem":13,
    "gn:feature_class":"P",
    "gn:feature_code":"PPL",
    "gn:name":"Round Rock",
    "gn:population":0,
    "gn:timezone":"America/Barbados",
    "iso:country":"BB",
    "wof:name":"Round Rock",
    "wof:placetype":"locality"
},
  "geometry": {"coordinates":[-59.51378,13.05042],"type":"Point"}
}