{
  "type": "Feature",
  "properties": {
    "gn:admin1_code":"10",
    "gn:asciiname":"Blades Hill",
    "gn:country_code":"BB",
    "gn:dem":74,
    "gn:feature_class":"P",
    "gn:feature_code":"PPL",
    "gn:name":"Blades Hill",
    "gn:population":0,
    "gn:timezone":"America/Barbados",
    "iso:country":"BB",
    "wof:name":"Blades Hill",
    "wof:placetype":"locality"
},
  "geometry": {"coordinates":[-59.4602,13.16238],"type":"Point"}
}