{
  "type": "Feature",
  "properties": {
    "gn:admin1_code":"07",
    "gn:asciiname":"Date Tree Hill",
    "gn:country_code":"BB",
    "gn:dem":95,
    "gn:feature_class":"P",
    "gn:feature_code":"PPL",
    "gn:name":"Date Tree Hill",
    "gn:population":0,
    "gn:timezone":"America/Barbados",
    "iso:country":"BB",
    "wof:name":"Date Tree Hill",
    "wof:placetype":"locality"
},
  "geometry": {"coordinates":[-59.58214,13.29228],"type":"Point"}
}