{
  "type": "Feature",
  "properties": {
    "gn:admin1_code":"09",
    "gn:asciiname":"Haymans Factory",
    "gn:country_code":"BB",
    "gn:dem":82,
    "gn:feature_class":"P",
    "gn:feature_code":"PPL",
    "gn:name":"Haymans Factory",
    "gn:population":0,
    "gn:timezone":"America/Barbados",
    "iso:country":"BB",
    "wof:name":"Haymans Factory",
    "wof:placetype":"locality"
},
  "geometry": {"coordinates":[-59.6285,13.24243],"type":"Point"}
}