{
  "type": "Feature",
  "properties": {
    "gn:admin1_code":"11",
    "gn:asciiname":"Poreys Spring",
    "gn:country_code":"BB",
    "gn:dem":235,
    "gn:feature_class":"P",
    "gn:feature_code":"PPL",
    "gn:name":"Poreys Spring",
    "gn:population":0,
    "gn:timezone":"America/Barbados",
    "iso:country":"BB",
    "wof:name":"Poreys Spring",
    "wof:placetype":"locality"
},
  "geometry": {"coordinates":[-59.59682,13.19282],"type":"Point"}
}