{
  "type": "Feature",
  "properties": {
    "gn:admin1_code":"00",
    "gn:asciiname":"Alleynedale",
    "gn:country_code":"BB",
    "gn:dem":81,
    "gn:feature_class":"P",
    "gn:feature_code":"PPL",
    "gn:name":"Alleynedale",
    "gn:population":0,
    "gn:timezone":"America/Barbados",
    "iso:country":"BB",
    "wof:name":"Alleynedale",
    "wof:placetype":"locality"
},
  "geometry": {"coordinates":[-59.62109,13.28385],"type":"Point"}
}