{
  "type": "Feature",
  "properties": {
    "iso:country":"BB",
    "name:bar_x_preferred":[
        "Maxwell"
    ],
    "name:ces_x_preferred":[
        "Maxwell"
    ],
    "name:dan_x_preferred":[
        "Maxwell"
    ],
    "name:deu_x_preferred":[
        "Maxwell"
    ],
    "name:eng_x_preferred":[
        "Maxwell"
    ],
    "name:fin_x_preferred":[
        "Maxwell"
    ],
    "name:fra_x_preferred":[
        "Maxwell"
    ],
    "name:gsw_x_preferred":[
        "Maxwell"
    ],
    "name:ita_x_preferred":[
        "Maxwell"
    ],
    "name:nds_x_preferred":[
        "Maxwell"
    ],
    "name:nld_x_preferred":[
        "Maxwell"
    ],
    "name:nno_x_preferred":[
        "Maxwell"
    ],
    "name:nob_x_preferred":[
        "Maxwell"
    ],
    "name:pol_x_preferred":[
        "Maxwell"
    ],
    "name:por_x_preferred":[
        "Maxwell"
    ],
    "name:spa_x_preferred":[
        "Maxwell"
    ],
    "name:swe_x_preferred":[
        "Maxwell"
    ],
    "name:tur_x_preferred":[
        "Maxwell"
    ],
    "qs:gn_country":"BB",
    "qs:gn_fcode":"PPL",
    "qs:gn_pop":0,
    "qs:name":"Maxwell",
    "qs:name_adm0":"Barbados",
    "qs:name_adm1":"Christ Church",
    "qs:photos":1612,
    "qs:photos_1k":327,
    "qs:photos_9k":7,
    "qs:photos_9r":8,
    "qs:photos_all":1612,
    "qs:photos_sr":13,
    "qs:placetype":"Town",
    "qs:pop_sr":"0",
    "qs:woe_adm0":23424754,
    "wd:wordcount":488,
    "wof:name":"Maxwell",
    "wof:placetype":"locality"
},
  "geometry": {"coordinates":[-59.55,13.06667],"type":"Point"}
}