{
  "type": "Feature",
  "properties": {
    "gn:admin1_code":"05",
    "gn:asciiname":"Hothersal",
    "gn:country_code":"BB",
    "gn:dem":263,
    "gn:feature_class":"P",
    "gn:feature_code":"PPL",
    "gn:name":"Hothersal",
    "gn:population":0,
    "gn:timezone":"America/Barbados",
    "iso:country":"BB",
    "wof:name":"Hothersal",
    "wof:placetype":"locality"
},
  "geometry": {"coordinates":[-59.51396999999999,13.19616],"type":"Point"}
}