{
  "type": "Feature",
  "properties": {
    "gn:admin1_code":"07",
    "gn:asciiname":"Mount Royer",
    "gn:country_code":"BB",
    "gn:dem":65,
    "gn:feature_class":"P",
    "gn:feature_code":"PPLL",
    "gn:name":"Mount Royer",
    "gn:population":0,
    "gn:timezone":"America/Barbados",
    "iso:country":"BB",
    "wof:name":"Mount Royer",
    "wof:placetype":"locality"
},
  "geometry": {"coordinates":[-59.62147,13.30749],"type":"Point"}
}