{
  "type": "Feature",
  "properties": {
    "gn:admin1_code":"07",
    "gn:asciiname":"Brome Field",
    "gn:country_code":"BB",
    "gn:dem":45,
    "gn:feature_class":"P",
    "gn:feature_code":"PPL",
    "gn:name":"Brome Field",
    "gn:population":0,
    "gn:timezone":"America/Barbados",
    "iso:country":"BB",
    "wof:name":"Brome Field",
    "wof:placetype":"locality"
},
  "geometry": {"coordinates":[-59.64435,13.29775],"type":"Point"}
}