{
  "type": "Feature",
  "properties": {
    "gn:admin1_code":"07",
    "gn:asciiname":"Bourbon",
    "gn:country_code":"BB",
    "gn:dem":52,
    "gn:feature_class":"P",
    "gn:feature_code":"PPL",
    "gn:name":"Bourbon",
    "gn:population":0,
    "gn:timezone":"America/Barbados",
    "iso:country":"BB",
    "wof:name":"Bourbon",
    "wof:placetype":"locality"
},
  "geometry": {"coordinates":[-59.6343,13.28921],"type":"Point"}
}