{
  "type": "Feature",
  "properties": {
    "gn:admin1_code":"07",
    "gn:asciiname":"Bourbon",
    "gn:country_code":"BB",
    "gn:dem":52,
    "gn:feature_class":"P",
    "gn:feature_code":"PPL",
    "gn:name":"Bourbon",
    "gn:population":0,
    "gn:timezone":"America/Barbados",
    "iso:country":"BB",
    "name:bos_x_preferred":[
        "Burbon"
    ],
    "name:bre_x_preferred":[
        "Bourbon"
    ],
    "name:cat_x_preferred":[
        "Bourbon"
    ],
    "name:ceb_x_preferred":[
        "Bourbon"
    ],
    "name:ces_x_preferred":[
        "Bourbon"
    ],
    "name:dan_x_preferred":[
        "Bourbon"
    ],
    "name:deu_x_preferred":[
        "Bourbon"
    ],
    "name:epo_x_preferred":[
        "Burbono"
    ],
    "name:fin_x_preferred":[
        "Bourbon"
    ],
    "name:fra_x_preferred":[
        "Bourbon"
    ],
    "name:heb_x_preferred":[
        "\u05d1\u05d5\u05e8\u05d1\u05d5\u05df"
    ],
    "name:hun_x_preferred":[
        "Bourbon"
    ],
    "name:ido_x_preferred":[
        "Bourbon"
    ],
    "name:ind_x_preferred":[
        "Bourbon"
    ],
    "name:ita_x_preferred":[
        "Bourbon"
    ],
    "name:jpn_x_preferred":[
        "\u30d0\u30fc\u30dc\u30f3"
    ],
    "name:nld_x_preferred":[
        "Bourbon"
    ],
    "name:nor_x_preferred":[
        "Bourbon"
    ],
    "name:pol_x_preferred":[
        "Bourbon"
    ],
    "name:por_x_preferred":[
        "Bourbon"
    ],
    "name:rus_x_preferred":[
        "\u0411\u0443\u0440\u0431\u043e\u043d"
    ],
    "name:spa_x_preferred":[
        "Bourbon"
    ],
    "name:srp_x_preferred":[
        "\u0411\u0443\u0440\u0431\u043e\u043d"
    ],
    "name:swe_x_preferred":[
        "Bourbon"
    ],
    "name:ukr_x_preferred":[
        "\u0411\u0443\u0440\u0431\u043e\u043d"
    ],
    "name:vol_x_preferred":[
        "Bourbon"
    ],
    "wof:name":"Bourbon",
    "wof:placetype":"locality"
},
  "geometry": {"coordinates":[-59.6343,13.28921],"type":"Point"}
}