{
  "type": "Feature",
  "properties": {
    "gn:admin1_code":"10",
    "gn:asciiname":"Sam Lords Castle",
    "gn:cc2":"BB",
    "gn:country_code":"BB",
    "gn:dem":18,
    "gn:feature_class":"P",
    "gn:feature_code":"PPL",
    "gn:name":"Sam Lords Castle",
    "gn:population":0,
    "gn:timezone":"America/Barbados",
    "iso:country":"BB",
    "name:und_x_variant":[
        "Lords Castle",
        "Sam Lords Castle"
    ],
    "wof:name":"Sam Lords Castle",
    "wof:placetype":"locality"
},
  "geometry": {"coordinates":[-59.4319,13.12542],"type":"Point"}
}