{
  "type": "Feature",
  "properties": {
    "iso:country":"BB",
    "qs:gn_country":"BB",
    "qs:gn_fcode":"PPL",
    "qs:gn_pop":0,
    "qs:name":"Belair",
    "qs:name_adm0":"Barbados",
    "qs:name_adm1":"Saint George",
    "qs:photos":1587,
    "qs:photos_1k":322,
    "qs:photos_9k":7,
    "qs:photos_9r":8,
    "qs:photos_all":1587,
    "qs:photos_sr":13,
    "qs:placetype":"Town",
    "qs:pop_sr":"0",
    "qs:woe_adm0":23424754,
    "wd:wordcount":97,
    "wof:name":"Belair",
    "wof:placetype":"locality"
},
  "geometry": {"coordinates":[-59.55,13.15],"type":"Point"}
}