{
  "type": "Feature",
  "properties": {
    "gn:asciiname":"Saint Lawrence Gap",
    "gn:country_code":"BB",
    "gn:dem":6,
    "gn:feature_class":"P",
    "gn:feature_code":"PPL",
    "gn:name":"Saint Lawrence Gap",
    "gn:population":0,
    "gn:timezone":"America/Barbados",
    "iso:country":"BB",
    "wof:name":"Saint Lawrence Gap",
    "wof:placetype":"locality"
},
  "geometry": {"coordinates":[-59.57516999999999,13.0679],"type":"Point"}
}