{
  "type": "Feature",
  "properties": {
    "gn:admin1_code":"09",
    "gn:asciiname":"Moore Hill",
    "gn:country_code":"BB",
    "gn:dem":190,
    "gn:feature_class":"P",
    "gn:feature_code":"PPL",
    "gn:name":"Moore Hill",
    "gn:population":0,
    "gn:timezone":"America/Barbados",
    "iso:country":"BB",
    "wof:name":"Moore Hill",
    "wof:placetype":"locality"
},
  "geometry": {"coordinates":[-59.59455,13.2767],"type":"Point"}
}