{
  "type": "Feature",
  "properties": {
    "gn:admin1_code":"01",
    "gn:asciiname":"Packers",
    "gn:country_code":"BB",
    "gn:dem":74,
    "gn:feature_class":"P",
    "gn:feature_code":"PPL",
    "gn:name":"Packers",
    "gn:population":0,
    "gn:timezone":"America/Barbados",
    "iso:country":"BB",
    "wof:name":"Packers",
    "wof:placetype":"locality"
},
  "geometry": {"coordinates":[-59.50408,13.09848],"type":"Point"}
}