{
  "type": "Feature",
  "properties": {
    "gn:admin1_code":"01",
    "gn:asciiname":"Pilgrim Road",
    "gn:country_code":"BB",
    "gn:dem":85,
    "gn:feature_class":"P",
    "gn:feature_code":"PPL",
    "gn:name":"Pilgrim Road",
    "gn:population":0,
    "gn:timezone":"America/Barbados",
    "iso:country":"BB",
    "wof:name":"Pilgrim Road",
    "wof:placetype":"locality"
},
  "geometry": {"coordinates":[-59.51217,13.07923],"type":"Point"}
}