{
  "type": "Feature",
  "properties": {
    "gn:admin1_code":"11",
    "gn:asciiname":"Bridgefield",
    "gn:country_code":"BB",
    "gn:dem":128,
    "gn:feature_class":"P",
    "gn:feature_code":"PPL",
    "gn:name":"Bridgefield",
    "gn:population":0,
    "gn:timezone":"America/Barbados",
    "iso:country":"BB",
    "wof:name":"Bridgefield",
    "wof:placetype":"locality"
},
  "geometry": {"coordinates":[-59.59007,13.15842],"type":"Point"}
}