{
  "type": "Feature",
  "properties": {
    "gn:admin1_code":"09",
    "gn:asciiname":"The Baltic",
    "gn:country_code":"BB",
    "gn:dem":141,
    "gn:feature_class":"P",
    "gn:feature_code":"PPL",
    "gn:name":"The Baltic",
    "gn:population":0,
    "gn:timezone":"America/Barbados",
    "iso:country":"BB",
    "wof:name":"The Baltic",
    "wof:placetype":"locality"
},
  "geometry": {"coordinates":[-59.58346,13.28805],"type":"Point"}
}