{
  "type": "Feature",
  "properties": {
    "iso:country":"BB",
    "name:deu_x_preferred":[
        "Cheapside"
    ],
    "name:eng_x_preferred":[
        "Cheapside"
    ],
    "name:epo_x_preferred":[
        "Cheapside"
    ],
    "name:fas_x_preferred":[
        "\u0686\u06cc\u067e\u0633\u0627\u06cc\u062f"
    ],
    "name:fin_x_preferred":[
        "Cheapside"
    ],
    "name:fra_x_preferred":[
        "Cheapside"
    ],
    "name:ind_x_preferred":[
        "Cheapside"
    ],
    "name:nor_x_preferred":[
        "Cheapside"
    ],
    "name:pol_x_preferred":[
        "Cheapside"
    ],
    "name:por_x_preferred":[
        "Cheapside"
    ],
    "name:tur_x_preferred":[
        "Cheapside"
    ],
    "name:zho_x_preferred":[
        "\u9f50\u666e\u8d5b\u8857"
    ],
    "qs:gn_local":0,
    "qs:local_max":3299,
    "qs:local_sum":5583,
    "qs:localhoods":7,
    "qs:name":"Cheapside",
    "qs:name_adm0":"Barbados",
    "qs:name_adm1":"Saint Michael",
    "qs:name_local":"Bridgetown",
    "qs:photo_max":209,
    "qs:photo_sum":1409,
    "qs:placetype":"Suburb",
    "qs:quad_count":42,
    "qs:woe_adm0":23424754,
    "qs:woe_adm1":2344737,
    "qs:woe_adm2":0,
    "qs:woe_lau":0,
    "qs:woe_local":56334,
    "qs:woe_ver":"7.10.0",
    "wd:wordcount":1682,
    "wof:lang":[
        "eng"
    ],
    "wof:name":"Cheapside",
    "wof:placetype":"neighbourhood"
},
  "geometry": {"coordinates":[-59.610205,13.081927],"type":"Point"}
}