{
  "type": "Feature",
  "properties": {
    "gn:admin1_code":"11",
    "gn:asciiname":"Allen View",
    "gn:country_code":"BB",
    "gn:dem":278,
    "gn:feature_class":"P",
    "gn:feature_code":"PPL",
    "gn:name":"Allen View",
    "gn:population":0,
    "gn:timezone":"America/Barbados",
    "iso:country":"BB",
    "wof:name":"Allen View",
    "wof:placetype":"locality"
},
  "geometry": {"coordinates":[-59.57418000000001,13.18664],"type":"Point"}
}