{
  "type": "Feature",
  "properties": {
    "gn:admin1_code":"07",
    "gn:asciiname":"Harrisons",
    "gn:country_code":"BB",
    "gn:dem":36,
    "gn:feature_class":"P",
    "gn:feature_code":"PPL",
    "gn:name":"Harrisons",
    "gn:population":0,
    "gn:timezone":"America/Barbados",
    "iso:country":"BB",
    "wof:name":"Harrisons",
    "wof:placetype":"locality"
},
  "geometry": {"coordinates":[-59.64892,13.30459],"type":"Point"}
}