{
  "type": "Feature",
  "properties": {
    "gn:admin1_code":"06",
    "gn:asciiname":"Airy Hill",
    "gn:country_code":"BB",
    "gn:dem":276,
    "gn:feature_class":"P",
    "gn:feature_code":"PPL",
    "gn:name":"Airy Hill",
    "gn:population":0,
    "gn:timezone":"America/Barbados",
    "iso:country":"BB",
    "wof:name":"Airy Hill",
    "wof:placetype":"locality"
},
  "geometry": {"coordinates":[-59.5557,13.18652],"type":"Point"}
}