{
  "type": "Feature",
  "properties": {
    "gn:admin1_code":"10",
    "gn:asciiname":"Whitehaven",
    "gn:country_code":"BB",
    "gn:dem":39,
    "gn:feature_class":"P",
    "gn:feature_code":"PPL",
    "gn:name":"Whitehaven",
    "gn:population":0,
    "gn:timezone":"America/Barbados",
    "iso:country":"BB",
    "wof:name":"Whitehaven",
    "wof:placetype":"locality"
},
  "geometry": {"coordinates":[-59.45234,13.16741],"type":"Point"}
}