{
  "type": "Feature",
  "properties": {
    "gn:admin1_code":"10",
    "gn:asciiname":"Whitehaven",
    "gn:country_code":"BB",
    "gn:dem":39,
    "gn:feature_class":"P",
    "gn:feature_code":"PPL",
    "gn:name":"Whitehaven",
    "gn:population":0,
    "gn:timezone":"America/Barbados",
    "iso:country":"BB",
    "name:azb_x_preferred":[
        "\u0648\u0647\u06cc\u062a\u0647\u0627\u0648\u0646"
    ],
    "name:bul_x_preferred":[
        "\u0423\u0430\u0439\u0442\u0445\u0435\u0439\u0432\u044a\u043d"
    ],
    "name:ceb_x_preferred":[
        "Whitehaven"
    ],
    "name:cym_x_preferred":[
        "Whitehaven"
    ],
    "name:dan_x_preferred":[
        "Whitehaven"
    ],
    "name:deu_x_preferred":[
        "Whitehaven"
    ],
    "name:fas_x_preferred":[
        "\u0648\u0647\u06cc\u062a\u0647\u0627\u0648\u0646"
    ],
    "name:fra_x_preferred":[
        "Whitehaven"
    ],
    "name:gle_x_preferred":[
        "Whitehaven"
    ],
    "name:glv_x_preferred":[
        "Whitehaven"
    ],
    "name:hun_x_preferred":[
        "Whitehaven"
    ],
    "name:ita_x_preferred":[
        "Whitehaven"
    ],
    "name:nld_x_preferred":[
        "Whitehaven"
    ],
    "name:nno_x_preferred":[
        "Whitehaven"
    ],
    "name:pol_x_preferred":[
        "Whitehaven"
    ],
    "name:por_x_preferred":[
        "Whitehaven"
    ],
    "name:ron_x_preferred":[
        "Whitehaven"
    ],
    "name:slk_x_preferred":[
        "Whitehaven"
    ],
    "name:spa_x_preferred":[
        "Whitehaven"
    ],
    "name:swe_x_preferred":[
        "Whitehaven"
    ],
    "name:urd_x_preferred":[
        "\u0648\u0627\u0626\u0679 \u06c1\u06cc\u0648\u0646"
    ],
    "name:zho_x_preferred":[
        "\u61f7\u7279\u6e2f"
    ],
    "wof:name":"Whitehaven",
    "wof:placetype":"locality"
},
  "geometry": {"coordinates":[-59.45234,13.16741],"type":"Point"}
}