{
  "type": "Feature",
  "properties": {
    "gn:admin1_code":"07",
    "gn:asciiname":"Fairfield",
    "gn:country_code":"BB",
    "gn:dem":79,
    "gn:feature_class":"P",
    "gn:feature_code":"PPL",
    "gn:name":"Fairfield",
    "gn:population":0,
    "gn:timezone":"America/Barbados",
    "iso:country":"BB",
    "wof:name":"Fairfield",
    "wof:placetype":"locality"
},
  "geometry": {"coordinates":[-59.62188,13.29431],"type":"Point"}
}