{
  "type": "Feature",
  "properties": {
    "gn:admin1_code":"04",
    "gn:asciiname":"Greenwich",
    "gn:country_code":"BB",
    "gn:dem":110,
    "gn:feature_class":"P",
    "gn:feature_code":"PPL",
    "gn:name":"Greenwich",
    "gn:population":0,
    "gn:timezone":"America/Barbados",
    "iso:country":"BB",
    "wof:name":"Greenwich",
    "wof:placetype":"locality"
},
  "geometry": {"coordinates":[-59.62207,13.19771],"type":"Point"}
}