{
  "type": "Feature",
  "properties": {
    "gn:admin1_code":"04",
    "gn:asciiname":"Weston",
    "gn:country_code":"BB",
    "gn:dem":26,
    "gn:feature_class":"P",
    "gn:feature_code":"PPL",
    "gn:name":"Weston",
    "gn:population":0,
    "gn:timezone":"America/Barbados",
    "iso:country":"BB",
    "name:ara_x_preferred":[
        "\u0648\u0633\u062a\u0648\u0646"
    ],
    "name:cat_x_preferred":[
        "Weston"
    ],
    "name:ceb_x_preferred":[
        "Weston"
    ],
    "name:ces_x_preferred":[
        "Weston"
    ],
    "name:cym_x_preferred":[
        "Weston"
    ],
    "name:deu_x_preferred":[
        "Weston"
    ],
    "name:fas_x_preferred":[
        "\u0648\u0633\u062a\u0648\u0646"
    ],
    "name:fra_x_preferred":[
        "Weston"
    ],
    "name:ido_x_preferred":[
        "Weston"
    ],
    "name:ita_x_preferred":[
        "Weston"
    ],
    "name:jpn_x_preferred":[
        "\u30a6\u30a8\u30b9\u30c8\u30f3"
    ],
    "name:kor_x_preferred":[
        "\uc6e8\uc2a4\ud134"
    ],
    "name:nld_x_preferred":[
        "Weston"
    ],
    "name:nor_x_preferred":[
        "Weston"
    ],
    "name:pol_x_preferred":[
        "Weston"
    ],
    "name:por_x_preferred":[
        "Weston"
    ],
    "name:rus_x_preferred":[
        "Weston"
    ],
    "name:sco_x_preferred":[
        "Weston"
    ],
    "name:spa_x_preferred":[
        "Weston"
    ],
    "name:srp_x_preferred":[
        "\u0412\u0435\u0441\u0442\u043e\u043d"
    ],
    "name:swe_x_preferred":[
        "Weston"
    ],
    "name:vol_x_preferred":[
        "Weston"
    ],
    "wof:name":"Weston",
    "wof:placetype":"locality"
},
  "geometry": {"coordinates":[-59.63864,13.215],"type":"Point"}
}