{
  "type": "Feature",
  "properties": {
    "gn:admin1_code":"04",
    "gn:asciiname":"Weston",
    "gn:country_code":"BB",
    "gn:dem":26,
    "gn:feature_class":"P",
    "gn:feature_code":"PPL",
    "gn:name":"Weston",
    "gn:population":0,
    "gn:timezone":"America/Barbados",
    "iso:country":"BB",
    "wof:name":"Weston",
    "wof:placetype":"locality"
},
  "geometry": {"coordinates":[-59.63864,13.215],"type":"Point"}
}