{
  "type": "Feature",
  "properties": {
    "gn:admin1_code":"10",
    "gn:asciiname":"Workhall",
    "gn:country_code":"BB",
    "gn:dem":41,
    "gn:feature_class":"P",
    "gn:feature_code":"PPL",
    "gn:name":"Workhall",
    "gn:population":0,
    "gn:timezone":"America/Barbados",
    "iso:country":"BB",
    "wof:name":"Workhall",
    "wof:placetype":"locality"
},
  "geometry": {"coordinates":[-59.45603000000001,13.12571],"type":"Point"}
}