{
  "type": "Feature",
  "properties": {
    "gn:admin1_code":"04",
    "gn:asciiname":"Molyneux",
    "gn:country_code":"BB",
    "gn:dem":60,
    "gn:feature_class":"P",
    "gn:feature_code":"PPL",
    "gn:name":"Molyneux",
    "gn:population":0,
    "gn:timezone":"America/Barbados",
    "iso:country":"BB",
    "wof:name":"Molyneux",
    "wof:placetype":"locality"
},
  "geometry": {"coordinates":[-59.62812,13.17815],"type":"Point"}
}