{
  "type": "Feature",
  "properties": {
    "gn:admin1_code":"03",
    "gn:asciiname":"Lower Estate",
    "gn:country_code":"BB",
    "gn:dem":72,
    "gn:feature_class":"P",
    "gn:feature_code":"PPL",
    "gn:name":"Lower Estate",
    "gn:population":0,
    "gn:timezone":"America/Barbados",
    "iso:country":"BB",
    "wof:name":"Lower Estate",
    "wof:placetype":"locality"
},
  "geometry": {"coordinates":[-59.57982,13.1334],"type":"Point"}
}