{
  "type": "Feature",
  "properties": {
    "gn:admin1_code":"11",
    "gn:asciiname":"Redmans",
    "gn:country_code":"BB",
    "gn:dem":149,
    "gn:feature_class":"P",
    "gn:feature_code":"PPL",
    "gn:name":"Redmans",
    "gn:population":0,
    "gn:timezone":"America/Barbados",
    "iso:country":"BB",
    "wof:name":"Redmans",
    "wof:placetype":"locality"
},
  "geometry": {"coordinates":[-59.61205,13.15914],"type":"Point"}
}