{
  "type": "Feature",
  "properties": {
    "gn:admin1_code":"07",
    "gn:asciiname":"Church Hill",
    "gn:country_code":"BB",
    "gn:dem":101,
    "gn:feature_class":"P",
    "gn:feature_code":"PPL",
    "gn:name":"Church Hill",
    "gn:population":0,
    "gn:timezone":"America/Barbados",
    "iso:country":"BB",
    "wof:name":"Church Hill",
    "wof:placetype":"locality"
},
  "geometry": {"coordinates":[-59.61911,13.28994],"type":"Point"}
}