{
  "type": "Feature",
  "properties": {
    "iso:country":"BB",
    "name:eng_x_preferred":[
        "Henrys"
    ],
    "qs:gn_local":0,
    "qs:local_max":3299,
    "qs:local_sum":5583,
    "qs:localhoods":7,
    "qs:name":"Henrys",
    "qs:name_adm0":"Barbados",
    "qs:name_adm1":"Saint Michael",
    "qs:name_local":"Bridgetown",
    "qs:photo_max":82,
    "qs:photo_sum":329,
    "qs:placetype":"Suburb",
    "qs:quad_count":16,
    "qs:woe_adm0":23424754,
    "qs:woe_adm1":2344737,
    "qs:woe_adm2":0,
    "qs:woe_lau":0,
    "qs:woe_local":56334,
    "qs:woe_ver":"7.10.0",
    "wd:wordcount":140,
    "wof:lang":[
        "eng"
    ],
    "wof:name":"Henrys",
    "wof:placetype":"neighbourhood"
},
  "geometry": {"coordinates":[-59.577685,13.071716],"type":"Point"}
}