{
  "type": "Feature",
  "properties": {
    "gn:admin1_code":"03",
    "gn:asciiname":"Watts Village",
    "gn:country_code":"BB",
    "gn:dem":66,
    "gn:feature_class":"P",
    "gn:feature_code":"PPL",
    "gn:name":"Watts Village",
    "gn:population":0,
    "gn:timezone":"America/Barbados",
    "iso:country":"BB",
    "wof:name":"Watts Village",
    "wof:placetype":"locality"
},
  "geometry": {"coordinates":[-59.53401,13.10943],"type":"Point"}
}