{
  "type": "Feature",
  "properties": {
    "gn:admin1_code":"04",
    "gn:asciiname":"Westmoreland",
    "gn:country_code":"BB",
    "gn:dem":126,
    "gn:feature_class":"P",
    "gn:feature_code":"PPL",
    "gn:name":"Westmoreland",
    "gn:population":0,
    "gn:timezone":"America/Barbados",
    "iso:country":"BB",
    "wof:name":"Westmoreland",
    "wof:placetype":"locality"
},
  "geometry": {"coordinates":[-59.62021,13.21672],"type":"Point"}
}