{
  "type": "Feature",
  "properties": {
    "gn:admin1_code":"04",
    "gn:asciiname":"Westmoreland",
    "gn:country_code":"BB",
    "gn:dem":126,
    "gn:feature_class":"P",
    "gn:feature_code":"PPL",
    "gn:name":"Westmoreland",
    "gn:population":0,
    "gn:timezone":"America/Barbados",
    "iso:country":"BB",
    "name:bre_x_preferred":[
        "Westmoreland"
    ],
    "name:cat_x_preferred":[
        "Westmoreland"
    ],
    "name:ceb_x_preferred":[
        "Westmoreland"
    ],
    "name:deu_x_preferred":[
        "Westmoreland"
    ],
    "name:fra_x_preferred":[
        "Westmoreland"
    ],
    "name:ita_x_preferred":[
        "Westmoreland"
    ],
    "name:jpn_x_preferred":[
        "\u30a6\u30a7\u30b9\u30c8\u30e2\u30fc\u30e9\u30f3\u30c9"
    ],
    "name:kor_x_preferred":[
        "\uc6e8\uc2a4\ud2b8\ubaa8\uc5bc\ub79c\ub4dc"
    ],
    "name:nld_x_preferred":[
        "Westmoreland"
    ],
    "name:nor_x_preferred":[
        "Westmoreland"
    ],
    "name:pol_x_preferred":[
        "Westmoreland"
    ],
    "name:por_x_preferred":[
        "Westmoreland"
    ],
    "name:rus_x_preferred":[
        "\u0423\u044d\u0441\u0442\u043c\u043e\u0440\u043b\u0435\u043d\u0434"
    ],
    "name:slk_x_preferred":[
        "Westmoreland"
    ],
    "name:srp_x_preferred":[
        "\u0412\u0435\u0441\u0442\u043c\u043e\u0440\u043b\u0430\u043d\u0434"
    ],
    "name:swe_x_preferred":[
        "Westmoreland"
    ],
    "name:vol_x_preferred":[
        "Westmoreland"
    ],
    "name:zho_x_preferred":[
        "\u5a01\u65af\u7279\u6469\u5170"
    ],
    "wof:name":"Westmoreland",
    "wof:placetype":"locality"
},
  "geometry": {"coordinates":[-59.62021,13.21672],"type":"Point"}
}