{
  "type": "Feature",
  "properties": {
    "gn:admin1_code":"07",
    "gn:asciiname":"Chance Hall",
    "gn:country_code":"BB",
    "gn:dem":43,
    "gn:feature_class":"P",
    "gn:feature_code":"PPL",
    "gn:name":"Chance Hall",
    "gn:population":0,
    "gn:timezone":"America/Barbados",
    "iso:country":"BB",
    "wof:name":"Chance Hall",
    "wof:placetype":"locality"
},
  "geometry": {"coordinates":[-59.60352,13.30988],"type":"Point"}
}