{
  "type": "Feature",
  "properties": {
    "gn:admin1_code":"08",
    "gn:asciiname":"Bibbys Lane",
    "gn:country_code":"BB",
    "gn:dem":111,
    "gn:feature_class":"P",
    "gn:feature_code":"PPL",
    "gn:name":"Bibbys Lane",
    "gn:population":0,
    "gn:timezone":"America/Barbados",
    "iso:country":"BB",
    "wof:name":"Bibbys Lane",
    "wof:placetype":"locality"
},
  "geometry": {"coordinates":[-59.58873000000001,13.15141],"type":"Point"}
}