{
  "type": "Feature",
  "properties": {
    "gn:admin1_code":"02",
    "gn:asciiname":"Turners Hall",
    "gn:country_code":"BB",
    "gn:dem":220,
    "gn:feature_class":"P",
    "gn:feature_code":"PPL",
    "gn:name":"Turners Hall",
    "gn:population":0,
    "gn:timezone":"America/Barbados",
    "iso:country":"BB",
    "wof:name":"Turners Hall",
    "wof:placetype":"locality"
},
  "geometry": {"coordinates":[-59.58809,13.2249],"type":"Point"}
}