{
  "type": "Feature",
  "properties": {
    "gn:admin1_code":"10",
    "gn:asciiname":"Robinsons",
    "gn:country_code":"BB",
    "gn:dem":31,
    "gn:feature_class":"P",
    "gn:feature_code":"PPL",
    "gn:name":"Robinsons",
    "gn:population":0,
    "gn:timezone":"America/Barbados",
    "iso:country":"BB",
    "name:lav_x_preferred":[
        "Robinsons"
    ],
    "wof:name":"Robinsons",
    "wof:placetype":"locality"
},
  "geometry": {"coordinates":[-59.44427,13.12805],"type":"Point"}
}