{
  "type": "Feature",
  "properties": {
    "gn:admin1_code":"04",
    "gn:asciiname":"Porters",
    "gn:country_code":"BB",
    "gn:dem":16,
    "gn:feature_class":"P",
    "gn:feature_code":"PPL",
    "gn:name":"Porters",
    "gn:population":0,
    "gn:timezone":"America/Barbados",
    "iso:country":"BB",
    "wof:name":"Porters",
    "wof:placetype":"locality"
},
  "geometry": {"coordinates":[-59.63946,13.20235],"type":"Point"}
}