{
  "type": "Feature",
  "properties": {
    "gn:admin1_code":"10",
    "gn:asciiname":"Saint Martins",
    "gn:country_code":"BB",
    "gn:dem":57,
    "gn:feature_class":"P",
    "gn:feature_code":"PPL",
    "gn:name":"Saint Martins",
    "gn:population":0,
    "gn:timezone":"America/Barbados",
    "iso:country":"BB",
    "wof:name":"Saint Martins",
    "wof:placetype":"locality"
},
  "geometry": {"coordinates":[-59.47054,13.09494],"type":"Point"}
}