{
  "type": "Feature",
  "properties": {
    "gn:admin1_code":"05",
    "gn:asciiname":"College Savannah",
    "gn:country_code":"BB",
    "gn:dem":40,
    "gn:feature_class":"P",
    "gn:feature_code":"PPL",
    "gn:name":"College Savannah",
    "gn:population":0,
    "gn:timezone":"America/Barbados",
    "iso:country":"BB",
    "wof:name":"College Savannah",
    "wof:placetype":"locality"
},
  "geometry": {"coordinates":[-59.45588000000001,13.17661],"type":"Point"}
}