{
  "type": "Feature",
  "properties": {
    "gn:admin1_code":"05",
    "gn:asciiname":"Massiah Street",
    "gn:cc2":"BB",
    "gn:country_code":"BB",
    "gn:dem":192,
    "gn:feature_class":"P",
    "gn:feature_code":"PPL",
    "gn:name":"Massiah Street",
    "gn:population":0,
    "gn:timezone":"America/Barbados",
    "iso:country":"BB",
    "name:und_x_variant":[
        "Rosegate",
        "Massiah Street"
    ],
    "wof:name":"Massiah Street",
    "wof:placetype":"locality"
},
  "geometry": {"coordinates":[-59.48399000000001,13.16217],"type":"Point"}
}