{
  "type": "Feature",
  "properties": {
    "gn:admin1_code":"06",
    "gn:asciiname":"Malvern",
    "gn:country_code":"BB",
    "gn:dem":278,
    "gn:feature_class":"P",
    "gn:feature_code":"PPL",
    "gn:name":"Malvern",
    "gn:population":0,
    "gn:timezone":"America/Barbados",
    "iso:country":"BB",
    "name:ceb_x_preferred":[
        "Malvern"
    ],
    "name:deu_x_preferred":[
        "Malvern"
    ],
    "name:fra_x_preferred":[
        "Malvern"
    ],
    "name:hun_x_preferred":[
        "Malvern"
    ],
    "name:ita_x_preferred":[
        "Malvern"
    ],
    "name:nld_x_preferred":[
        "Malvern"
    ],
    "name:pol_x_preferred":[
        "Malvern"
    ],
    "name:por_x_preferred":[
        "Malvern"
    ],
    "name:rus_x_preferred":[
        "\u041c\u0430\u043b\u0432\u0435\u0440\u043d"
    ],
    "name:spa_x_preferred":[
        "Malvern"
    ],
    "name:srp_x_preferred":[
        "\u041c\u0430\u043b\u0432\u0435\u0440\u043d"
    ],
    "name:swe_x_preferred":[
        "Malvern"
    ],
    "name:ukr_x_preferred":[
        "\u041c\u0430\u043b\u0432\u0435\u0440\u043d"
    ],
    "name:vol_x_preferred":[
        "Malvern"
    ],
    "wof:name":"Malvern",
    "wof:placetype":"locality"
},
  "geometry": {"coordinates":[-59.52599,13.19411],"type":"Point"}
}