{
  "type": "Feature",
  "properties": {
    "gn:admin1_code":"07",
    "gn:asciiname":"Hope",
    "gn:country_code":"BB",
    "gn:dem":24,
    "gn:feature_class":"P",
    "gn:feature_code":"PPL",
    "gn:name":"Hope",
    "gn:population":0,
    "gn:timezone":"America/Barbados",
    "iso:country":"BB",
    "wof:name":"Hope",
    "wof:placetype":"locality"
},
  "geometry": {"coordinates":[-59.6038,13.32043],"type":"Point"}
}