{
  "type": "Feature",
  "properties": {
    "gn:admin1_code":"07",
    "gn:asciiname":"Archers",
    "gn:cc2":"BB",
    "gn:country_code":"BB",
    "gn:dem":36,
    "gn:feature_class":"P",
    "gn:feature_code":"PPL",
    "gn:name":"Archers",
    "gn:population":0,
    "gn:timezone":"America/Barbados",
    "iso:country":"BB",
    "name:und_x_variant":[
        "Archer",
        "Archers"
    ],
    "wof:name":"Archers",
    "wof:placetype":"locality"
},
  "geometry": {"coordinates":[-59.6396,13.31832],"type":"Point"}
}