{
  "type": "Feature",
  "properties": {
    "gn:admin1_code":"10",
    "gn:asciiname":"Thicket",
    "gn:country_code":"BB",
    "gn:dem":89,
    "gn:feature_class":"P",
    "gn:feature_code":"PPL",
    "gn:name":"Thicket",
    "gn:population":0,
    "gn:timezone":"America/Barbados",
    "iso:country":"BB",
    "name:ara_x_preferred":[
        "\u062f\u063a\u0644"
    ],
    "name:cat_x_preferred":[
        "Bardissa"
    ],
    "name:dan_x_preferred":[
        "Krat"
    ],
    "name:deu_x_preferred":[
        "Dickicht"
    ],
    "name:epo_x_preferred":[
        "Densa\u0135o"
    ],
    "name:fas_x_preferred":[
        "\u0628\u06cc\u0634\u0647"
    ],
    "name:fra_x_preferred":[
        "Fourr\u00e9"
    ],
    "name:hrv_x_preferred":[
        "\u0160ikara"
    ],
    "name:ido_x_preferred":[
        "Busho"
    ],
    "name:jpn_x_preferred":[
        "\u96d1\u6728\u6797"
    ],
    "name:srp_x_preferred":[
        "\u0428\u0438\u043a\u0430\u0440\u0430"
    ],
    "wof:name":"Thicket",
    "wof:placetype":"locality"
},
  "geometry": {"coordinates":[-59.46425,13.15588],"type":"Point"}
}