{
  "type": "Feature",
  "properties": {
    "gn:admin1_code":"10",
    "gn:asciiname":"Thicket",
    "gn:country_code":"BB",
    "gn:dem":89,
    "gn:feature_class":"P",
    "gn:feature_code":"PPL",
    "gn:name":"Thicket",
    "gn:population":0,
    "gn:timezone":"America/Barbados",
    "iso:country":"BB",
    "wof:name":"Thicket",
    "wof:placetype":"locality"
},
  "geometry": {"coordinates":[-59.46425,13.15588],"type":"Point"}
}