{
  "type": "Feature",
  "properties": {
    "gn:admin1_code":"07",
    "gn:asciiname":"Coconut Hall",
    "gn:country_code":"BB",
    "gn:dem":22,
    "gn:feature_class":"P",
    "gn:feature_code":"PPL",
    "gn:name":"Coconut Hall",
    "gn:population":0,
    "gn:timezone":"America/Barbados",
    "iso:country":"BB",
    "wof:name":"Coconut Hall",
    "wof:placetype":"locality"
},
  "geometry": {"coordinates":[-59.60029,13.32031],"type":"Point"}
}