{
  "type": "Feature",
  "properties": {
    "gn:admin1_code":"04",
    "gn:asciiname":"Folkestone Park",
    "gn:country_code":"BB",
    "gn:dem":57,
    "gn:feature_class":"P",
    "gn:feature_code":"PPL",
    "gn:name":"Folkestone Park",
    "gn:population":0,
    "gn:timezone":"America/Barbados",
    "iso:country":"BB",
    "wof:name":"Folkestone Park",
    "wof:placetype":"locality"
},
  "geometry": {"coordinates":[-59.62942,13.18177],"type":"Point"}
}